aa_captrack-1.0.8.dist-info/licenses/LICENSE
captrack/__init__.py
captrack/admin.py
captrack/apps.py
captrack/constants.py
captrack/helpers.py
captrack/hooks.py
captrack/models.py
captrack/services.py
captrack/tasks.py
captrack/urls.py
captrack/views.py
captrack/migrations/0001_initial.py
captrack/migrations/0002_alter_captracksettings_options.py
captrack/migrations/0003_alter_captracksettings_options.py
captrack/migrations/0004_update_basic_access_permission_name.py
captrack/migrations/0005_capwatchlist_alert_snoozed_until_and_more.py
captrack/migrations/0006_captracksettings_discord_mentions.py
captrack/migrations/__init__.py
captrack/templates/captrack/dashboard .bak
captrack/templates/captrack/dashboard.html
captrack/utils/__init__.py
captrack/utils/discord.py
testproj/__init__.py
testproj/apps.py
testproj/manage.py
testproj/models-mock.py
testproj/settings.py
testproj/testproj/__init__.py
testproj/testproj/asgi.py
testproj/testproj/settings.py
testproj/testproj/urls.py
testproj/testproj/wsgi.py
aa_captrack-1.0.8.dist-info/METADATA
aa_captrack-1.0.8.dist-info/WHEEL
aa_captrack-1.0.8.dist-info/top_level.txt
aa_captrack-1.0.8.dist-info/RECORD
