Metadata-Version: 2.4
Name: aa-captrack
Version: 1.0.8
Summary: Capital ship movement early warning plugin for AllianceAuth
Home-page: https://github.com/SteveTh3Piirate/aa-captrack
Author: SteveTh3Piirate
License: MIT
Project-URL: Source, https://github.com/SteveTh3Piirate/aa-captrack
Project-URL: Issues, https://github.com/SteveTh3Piirate/aa-captrack/issues
Classifier: Framework :: Django
Classifier: Framework :: Django :: 4.2
Classifier: License :: OSI Approved :: MIT License
Classifier: Programming Language :: Python :: 3
Classifier: Programming Language :: Python :: 3 :: Only
Classifier: Programming Language :: Python :: 3.10
Classifier: Programming Language :: Python :: 3.11
Requires-Python: >=3.10
License-File: LICENSE
Requires-Dist: allianceauth>=4.0
Requires-Dist: allianceauth-corptools>=2.15.2
Requires-Dist: requests>=2.0
Dynamic: author
Dynamic: classifier
Dynamic: description
Dynamic: description-content-type
Dynamic: home-page
Dynamic: license
Dynamic: license-file
Dynamic: project-url
Dynamic: requires-dist
Dynamic: requires-python
Dynamic: summary
